{"id":"acucar-refinado-isendo-de-mofo-fermenta-bfcf1304","nome":"Açucar refinado isendo de mofo, fermentação, odores estranhos e substância nocivas. Embalagem primária: pacote de 1kg, val. mínima 12 meses a contar a partir da data de entrega.","nome_norm":"acucar refinado isendo de mofo, fermentacao, odores estranhos e substancia nociv","categoria":"Alimentação e Gêneros Alimentícios","unidade":"kg","tipo":"M","sneaelis":false,"preco":{"min":5.8,"p25":5.98,"mediana":6.17,"media":6.17,"p75":6.36,"p90":6.47,"max":6.54,"desvio":0.52,"n":2},"srp_pct":50.0,"serie_temporal":[{"mes":"2025-08","mediana":6.17,"n":2,"min":5.8,"max":6.54}],"por_municipio":[{"municipio":"Anajás","mediana":6.54,"n":1,"min":6.54,"max":6.54},{"municipio":"Muaná","mediana":5.8,"n":1,"min":5.8,"max":5.8}],"ocorrencias":[{"mes":"2025-08","municipio":"Muaná","valor_unitario":5.8,"quantidade":10848.0,"unidade":"kg","srp":true,"modalidade_nome":"Pregão - Eletrônico","cnpj_orgao":"05105200000122","sequencial_compra":54},{"mes":"2025-08","municipio":"Anajás","valor_unitario":6.54,"quantidade":12600.0,"unidade":"unidade","srp":false,"modalidade_nome":"Pregão - Eletrônico","cnpj_orgao":"05849955000131","sequencial_compra":25}]}