{"id":"algema-df18d198","nome":"Algema","nome_norm":"algema","categoria":"Outros","unidade":"unidade","tipo":"M","sneaelis":false,"preco":{"min":115.33,"p25":152.16,"mediana":189.0,"media":206.04,"p75":251.39,"p90":288.83,"max":313.79,"desvio":100.32,"n":3},"srp_pct":100.0,"serie_temporal":[{"mes":"2025-01","mediana":313.79,"n":1,"min":313.79,"max":313.79},{"mes":"2025-09","mediana":152.16,"n":2,"min":115.33,"max":189.0}],"por_municipio":[{"municipio":"Belém","mediana":251.39,"n":2,"min":189.0,"max":313.79},{"municipio":"Altamira","mediana":115.33,"n":1,"min":115.33,"max":115.33}],"ocorrencias":[{"mes":"2025-09","municipio":"Altamira","valor_unitario":115.33,"quantidade":20.0,"unidade":"unidade","srp":true,"modalidade_nome":"Pregão - Eletrônico","cnpj_orgao":"00394452000103","sequencial_compra":18989},{"mes":"2025-09","municipio":"Belém","valor_unitario":189.0,"quantidade":30.0,"unidade":"unidade","srp":true,"modalidade_nome":"Pregão - Eletrônico","cnpj_orgao":"00394429000100","sequencial_compra":2460},{"mes":"2025-01","municipio":"Belém","valor_unitario":313.79,"quantidade":13400.0,"unidade":"unidade","srp":true,"modalidade_nome":"Pregão - Eletrônico","cnpj_orgao":"05054994000142","sequencial_compra":42}]}