{"id":"aluguel-e-montagem-de-andaime-metalico-66341921","nome":"Aluguel e montagem de andaime metálico","nome_norm":"aluguel e montagem de andaime metalico","categoria":"Outros","unidade":"metro quadrado por m","tipo":"S","sneaelis":false,"preco":{"min":25.09,"p25":25.15,"mediana":25.2,"media":25.2,"p75":25.26,"p90":25.3,"max":25.32,"desvio":0.16,"n":2},"srp_pct":50.0,"serie_temporal":[{"mes":"2025-05","mediana":25.09,"n":1,"min":25.09,"max":25.09},{"mes":"2025-12","mediana":25.32,"n":1,"min":25.32,"max":25.32}],"por_municipio":[{"municipio":"Ananindeua","mediana":25.2,"n":2,"min":25.09,"max":25.32}],"ocorrencias":[{"mes":"2025-05","municipio":"Ananindeua","valor_unitario":25.09,"quantidade":300.0,"unidade":"metro quadrado por m","srp":true,"modalidade_nome":"Pregão - Eletrônico","cnpj_orgao":"00423755000107","sequencial_compra":3},{"mes":"2025-12","municipio":"Ananindeua","valor_unitario":25.32,"quantidade":160.0,"unidade":"metro quadrado por m","srp":false,"modalidade_nome":"Pregão - Eletrônico","cnpj_orgao":"00423755000107","sequencial_compra":14}]}