{"id":"aparelho-ar-condicionado-tipo-split-917a2ac0","nome":"Aparelho Ar Condicionado / Tipo: Split / Modelo: Split\nInverter / Capacidade Refrigeração: 24.000 BTU / Tensão:\n110/220 V / Características Adicionais 1: Controle\nRemoto/Display Digital/Timer/Selo Procel - Tipo: Hi-Wall /\nModelo: Split Inverter / Capacidade Refrigeração: 24.000 BTU/H\n/ Tensão: 220 V / Freqüência: 60 HZ / Garantia: 1 ANO / Filtro\nAntibactéria, Desumidificação\n","nome_norm":"aparelho ar condicionado / tipo: split / modelo: split inverter / capacidade ref","categoria":"Mobiliário e Equipamentos Gerais","unidade":"unidade","tipo":"M","sneaelis":true,"preco":{"min":4671.85,"p25":6100.26,"mediana":7528.66,"media":8382.04,"p75":10237.14,"p90":11862.23,"max":12945.62,"desvio":4202.38,"n":3},"srp_pct":100.0,"serie_temporal":[{"mes":"2025-09","mediana":7528.66,"n":3,"min":4671.85,"max":12945.62}],"por_municipio":[{"municipio":"Breves","mediana":7528.66,"n":3,"min":4671.85,"max":12945.62}],"ocorrencias":[{"mes":"2025-09","municipio":"Breves","valor_unitario":4671.85,"quantidade":80.0,"unidade":"unidade","srp":true,"modalidade_nome":"Pregão - Eletrônico","cnpj_orgao":"17298800000133","sequencial_compra":16},{"mes":"2025-09","municipio":"Breves","valor_unitario":7528.66,"quantidade":25.0,"unidade":"unidade","srp":true,"modalidade_nome":"Pregão - Eletrônico","cnpj_orgao":"17298800000133","sequencial_compra":16},{"mes":"2025-09","municipio":"Breves","valor_unitario":12945.62,"quantidade":26.0,"unidade":"unidade","srp":true,"modalidade_nome":"Pregão - Eletrônico","cnpj_orgao":"17298800000133","sequencial_compra":16}]}