{"id":"arroz-branco-especificacao-tipo-1-lon-723ded94","nome":"ARROZ BRANCO, Especificação: tipo 1, longo fino, constituídos de grãos inteiros, com teor de umidade máxima 15, isento de sujidades e materiais estranhos, embalagem de 1 kg em sacos plásticos transparentes e atóxicos, limpos não violados, resistentes que garantam a integridade do produto até o momento do consumo acondicionados em fardos lacrados. A embalagem deverá conter externamente os dados de identificação e procedência, informação nutricional, número do lote, data de validade, quantidade do produto. O produto deverá apresentar validade mínima de 06 (seis) meses a partir da data de entrega na unidade requisitam longo fino, tipo I, cor branca, e sem sujidades / parasitas / larvas / bolores, subgrupo polido. Pacote de 1 kg e fardo com até 30kg.","nome_norm":"arroz branco, especificacao: tipo 1, longo fino, constituidos de graos inteiros,","categoria":"Alimentação e Gêneros Alimentícios","unidade":"kg","tipo":"M","sneaelis":false,"preco":{"min":8.63,"p25":10.35,"mediana":12.06,"media":12.06,"p75":13.78,"p90":14.8,"max":15.49,"desvio":4.85,"n":2},"srp_pct":100.0,"serie_temporal":[{"mes":"2025-01","mediana":15.49,"n":1,"min":15.49,"max":15.49},{"mes":"2025-12","mediana":8.63,"n":1,"min":8.63,"max":8.63}],"por_municipio":[{"municipio":"Senador José Porfírio","mediana":12.06,"n":2,"min":8.63,"max":15.49}],"ocorrencias":[{"mes":"2025-12","municipio":"Senador José Porfírio","valor_unitario":8.63,"quantidade":45500.0,"unidade":"kg","srp":true,"modalidade_nome":"Pregão - Eletrônico","cnpj_orgao":"13810386000149","sequencial_compra":12},{"mes":"2025-01","municipio":"Senador José Porfírio","valor_unitario":15.49,"quantidade":20000.0,"unidade":"kg","srp":true,"modalidade_nome":"Pregão - Eletrônico","cnpj_orgao":"13810386000149","sequencial_compra":1}]}