{"id":"bolsa-9cdebedc","nome":"Bolsa","nome_norm":"bolsa","categoria":"Outros","unidade":"unidade","tipo":"M","sneaelis":false,"preco":{"min":19.27,"p25":71.08,"mediana":145.86,"media":64226.58,"p75":165.68,"p90":116277.33,"max":575960.0,"desvio":191900.49,"n":9},"srp_pct":66.7,"serie_temporal":[{"mes":"2025-04","mediana":145.86,"n":1,"min":145.86,"max":145.86},{"mes":"2025-06","mediana":71.08,"n":3,"min":19.27,"max":1356.66},{"mes":"2025-08","mediana":288000.76,"n":2,"min":41.53,"max":575960.0},{"mes":"2025-09","mediana":155.31,"n":1,"min":155.31,"max":155.31},{"mes":"2025-10","mediana":144.74,"n":2,"min":123.8,"max":165.68}],"por_municipio":[{"municipio":"Belém","mediana":713.87,"n":4,"min":19.27,"max":575960.0},{"municipio":"Bonito","mediana":144.74,"n":2,"min":123.8,"max":165.68},{"municipio":"Marituba","mediana":155.31,"n":1,"min":155.31,"max":155.31},{"municipio":"Pacajá","mediana":145.86,"n":1,"min":145.86,"max":145.86},{"municipio":"Santa Bárbara do Pará","mediana":41.53,"n":1,"min":41.53,"max":41.53}],"ocorrencias":[{"mes":"2025-06","municipio":"Belém","valor_unitario":19.27,"quantidade":150.0,"unidade":"unidade","srp":false,"modalidade_nome":"Dispensa","cnpj_orgao":"10763998000130","sequencial_compra":54},{"mes":"2025-08","municipio":"Santa Bárbara do Pará","valor_unitario":41.53,"quantidade":400.0,"unidade":"unidade","srp":true,"modalidade_nome":"Pregão - Eletrônico","cnpj_orgao":"83334698000109","sequencial_compra":16},{"mes":"2025-06","municipio":"Belém","valor_unitario":71.08,"quantidade":50.0,"unidade":"unidade","srp":false,"modalidade_nome":"Pregão - Eletrônico","cnpj_orgao":"05914737000133","sequencial_compra":2},{"mes":"2025-10","municipio":"Bonito","valor_unitario":123.8,"quantidade":20.0,"unidade":"unidade","srp":true,"modalidade_nome":"Pregão - Eletrônico","cnpj_orgao":"05149083000107","sequencial_compra":29},{"mes":"2025-04","municipio":"Pacajá","valor_unitario":145.86,"quantidade":500.0,"unidade":"unidade","srp":true,"modalidade_nome":"Pregão - Eletrônico","cnpj_orgao":"22981427000150","sequencial_compra":8},{"mes":"2025-09","municipio":"Marituba","valor_unitario":155.31,"quantidade":500.0,"unidade":"unidade","srp":true,"modalidade_nome":"Pregão - Eletrônico","cnpj_orgao":"01611666000149","sequencial_compra":40},{"mes":"2025-10","municipio":"Bonito","valor_unitario":165.68,"quantidade":110.0,"unidade":"unidade","srp":true,"modalidade_nome":"Pregão - Eletrônico","cnpj_orgao":"05149083000107","sequencial_compra":29},{"mes":"2025-06","municipio":"Belém","valor_unitario":1356.66,"quantidade":18.0,"unidade":"unidade","srp":true,"modalidade_nome":"Pregão - Eletrônico","cnpj_orgao":"00394502002864","sequencial_compra":82},{"mes":"2025-08","municipio":"Belém","valor_unitario":575960.0,"quantidade":1.0,"unidade":"unidade","srp":false,"modalidade_nome":"Pregão - Eletrônico","cnpj_orgao":"37205760000145","sequencial_compra":5}]}