{"id":"botas-para-eletricista-tam-38-a-43-934b3dcd","nome":"BOTAS PARA ELETRICISTA TAM 38 a 43","nome_norm":"botas para eletricista tam 38 a 43","categoria":"Outros","unidade":"par","tipo":"M","sneaelis":false,"preco":{"min":92.37,"p25":99.21,"mediana":106.05,"media":106.05,"p75":112.88,"p90":116.98,"max":119.72,"desvio":19.34,"n":2},"srp_pct":100.0,"serie_temporal":[{"mes":"2025-03","mediana":92.37,"n":1,"min":92.37,"max":92.37},{"mes":"2025-10","mediana":119.72,"n":1,"min":119.72,"max":119.72}],"por_municipio":[{"municipio":"Uruará","mediana":106.04,"n":2,"min":92.37,"max":119.72}],"ocorrencias":[{"mes":"2025-03","municipio":"Uruará","valor_unitario":92.37,"quantidade":40.0,"unidade":"par","srp":true,"modalidade_nome":"Pregão - Eletrônico","cnpj_orgao":"34593541000192","sequencial_compra":36},{"mes":"2025-10","municipio":"Uruará","valor_unitario":119.72,"quantidade":60.0,"unidade":"par","srp":true,"modalidade_nome":"Pregão - Eletrônico","cnpj_orgao":"34593541000192","sequencial_compra":89}]}