{"id":"bucha-bronze-2908ab1c","nome":"Bucha Bronze","nome_norm":"bucha bronze","categoria":"Outros","unidade":"unidade","tipo":"M","sneaelis":false,"preco":{"min":3800.0,"p25":5787.5,"mediana":7775.0,"media":7775.0,"p75":9762.5,"p90":10955.0,"max":11750.0,"desvio":5621.5,"n":2},"srp_pct":0.0,"serie_temporal":[{"mes":"2025-05","mediana":7775.0,"n":2,"min":3800.0,"max":11750.0}],"por_municipio":[{"municipio":"Belém","mediana":7775.0,"n":2,"min":3800.0,"max":11750.0}],"ocorrencias":[{"mes":"2025-05","municipio":"Belém","valor_unitario":3800.0,"quantidade":1.0,"unidade":"unidade","srp":false,"modalidade_nome":"Dispensa","cnpj_orgao":"00394502000144","sequencial_compra":4516},{"mes":"2025-05","municipio":"Belém","valor_unitario":11750.0,"quantidade":1.0,"unidade":"unidade","srp":false,"modalidade_nome":"Dispensa","cnpj_orgao":"00394502000144","sequencial_compra":4516}]}