{"id":"destilador-agua-be299a79","nome":"Destilador Água","nome_norm":"destilador agua","categoria":"Outros","unidade":"unidade","tipo":"M","sneaelis":false,"preco":{"min":2924.2,"p25":3088.85,"mediana":3253.5,"media":3292.57,"p75":3476.75,"p90":3610.7,"max":3700.0,"desvio":389.37,"n":3},"srp_pct":0.0,"serie_temporal":[{"mes":"2025-01","mediana":3700.0,"n":1,"min":3700.0,"max":3700.0},{"mes":"2025-08","mediana":2924.2,"n":1,"min":2924.2,"max":2924.2},{"mes":"2025-12","mediana":3253.5,"n":1,"min":3253.5,"max":3253.5}],"por_municipio":[{"municipio":"Belém","mediana":3253.5,"n":3,"min":2924.2,"max":3700.0}],"ocorrencias":[{"mes":"2025-08","municipio":"Belém","valor_unitario":2924.2,"quantidade":1.0,"unidade":"unidade","srp":false,"modalidade_nome":"Pregão - Eletrônico","cnpj_orgao":"34860833000144","sequencial_compra":48},{"mes":"2025-12","municipio":"Belém","valor_unitario":3253.5,"quantidade":1.0,"unidade":"unidade","srp":false,"modalidade_nome":"Pregão - Eletrônico","cnpj_orgao":"05321731000152","sequencial_compra":27},{"mes":"2025-01","municipio":"Belém","valor_unitario":3700.0,"quantidade":1.0,"unidade":"unidade","srp":false,"modalidade_nome":"Dispensa","cnpj_orgao":"34621748000123","sequencial_compra":5}]}