{"id":"diaria-tratorista-b45de9e4","nome":"DIARIA - TRATORISTA","nome_norm":"diaria - tratorista","categoria":"Outros","unidade":"diaria","tipo":"S","sneaelis":false,"preco":{"min":70.0,"p25":70.0,"mediana":70.0,"media":70.0,"p75":70.0,"p90":70.0,"max":70.0,"desvio":0.0,"n":3},"srp_pct":0.0,"serie_temporal":[{"mes":"2025-01","mediana":70.0,"n":1,"min":70.0,"max":70.0},{"mes":"2025-03","mediana":70.0,"n":1,"min":70.0,"max":70.0},{"mes":"2025-04","mediana":70.0,"n":1,"min":70.0,"max":70.0}],"por_municipio":[{"municipio":"Palestina do Pará","mediana":70.0,"n":3,"min":70.0,"max":70.0}],"ocorrencias":[{"mes":"2025-01","municipio":"Palestina do Pará","valor_unitario":70.0,"quantidade":15.0,"unidade":"diaria","srp":false,"modalidade_nome":"Dispensa","cnpj_orgao":"83211417000120","sequencial_compra":21},{"mes":"2025-03","municipio":"Palestina do Pará","valor_unitario":70.0,"quantidade":10.0,"unidade":"diaria","srp":false,"modalidade_nome":"Dispensa","cnpj_orgao":"83211417000120","sequencial_compra":103},{"mes":"2025-04","municipio":"Palestina do Pará","valor_unitario":70.0,"quantidade":4.0,"unidade":"diaria","srp":false,"modalidade_nome":"Dispensa","cnpj_orgao":"83211417000120","sequencial_compra":133}]}