{"id":"empilhadeira-b22b0e93","nome":"Empilhadeira","nome_norm":"empilhadeira","categoria":"Outros","unidade":"unidade","tipo":"M","sneaelis":false,"preco":{"min":6262.28,"p25":53092.39,"mediana":99922.5,"media":92680.1,"p75":135889.02,"p90":157468.92,"max":171855.53,"desvio":83033.85,"n":3},"srp_pct":66.7,"serie_temporal":[{"mes":"2025-01","mediana":6262.28,"n":1,"min":6262.28,"max":6262.28},{"mes":"2025-09","mediana":171855.53,"n":1,"min":171855.53,"max":171855.53},{"mes":"2025-10","mediana":99922.5,"n":1,"min":99922.5,"max":99922.5}],"por_municipio":[{"municipio":"Belém","mediana":135889.02,"n":2,"min":99922.5,"max":171855.53},{"municipio":"Itaituba","mediana":6262.28,"n":1,"min":6262.28,"max":6262.28}],"ocorrencias":[{"mes":"2025-01","municipio":"Itaituba","valor_unitario":6262.28,"quantidade":1.0,"unidade":"unidade","srp":true,"modalidade_nome":"Pregão - Eletrônico","cnpj_orgao":"00394544000185","sequencial_compra":118},{"mes":"2025-10","municipio":"Belém","valor_unitario":99922.5,"quantidade":2.0,"unidade":"unidade","srp":true,"modalidade_nome":"Pregão - Eletrônico","cnpj_orgao":"00394502000144","sequencial_compra":9320},{"mes":"2025-09","municipio":"Belém","valor_unitario":171855.53,"quantidade":1.0,"unidade":"unidade","srp":false,"modalidade_nome":"Pregão - Eletrônico","cnpj_orgao":"05055009000113","sequencial_compra":18}]}