{"id":"equipamento-videoconferencia-d5621574","nome":"Equipamento videoconferência","nome_norm":"equipamento videoconferencia","categoria":"Outros","unidade":"unidade","tipo":"M","sneaelis":false,"preco":{"min":7729.33,"p25":8733.48,"mediana":11219.76,"media":40670.63,"p75":43156.91,"p90":96770.96,"max":132513.66,"desvio":61275.98,"n":4},"srp_pct":75.0,"serie_temporal":[{"mes":"2025-03","mediana":9068.2,"n":1,"min":9068.2,"max":9068.2},{"mes":"2025-05","mediana":7729.33,"n":1,"min":7729.33,"max":7729.33},{"mes":"2025-08","mediana":72942.5,"n":2,"min":13371.33,"max":132513.66}],"por_municipio":[{"municipio":"Belém","mediana":13371.33,"n":3,"min":7729.33,"max":132513.66},{"municipio":"Marabá","mediana":9068.2,"n":1,"min":9068.2,"max":9068.2}],"ocorrencias":[{"mes":"2025-05","municipio":"Belém","valor_unitario":7729.33,"quantidade":1.0,"unidade":"unidade","srp":false,"modalidade_nome":"Dispensa","cnpj_orgao":"04974325000126","sequencial_compra":9},{"mes":"2025-03","municipio":"Marabá","valor_unitario":9068.2,"quantidade":6.0,"unidade":"unidade","srp":true,"modalidade_nome":"Pregão - Eletrônico","cnpj_orgao":"18657063000180","sequencial_compra":8},{"mes":"2025-08","municipio":"Belém","valor_unitario":13371.33,"quantidade":500.0,"unidade":"unidade","srp":true,"modalidade_nome":"Pregão - Eletrônico","cnpj_orgao":"04567897000190","sequencial_compra":81},{"mes":"2025-08","municipio":"Belém","valor_unitario":132513.66,"quantidade":2.0,"unidade":"unidade","srp":true,"modalidade_nome":"Pregão - Eletrônico","cnpj_orgao":"21744847000150","sequencial_compra":1062}]}