{"id":"escada-hospitalar-a655fd7a","nome":"Escada Hospitalar","nome_norm":"escada hospitalar","categoria":"Outros","unidade":"unidade","tipo":"M","sneaelis":false,"preco":{"min":235.0,"p25":369.7,"mediana":504.4,"media":422.52,"p75":516.27,"p90":523.4,"max":528.15,"desvio":162.83,"n":3},"srp_pct":0.0,"serie_temporal":[{"mes":"2025-02","mediana":516.28,"n":2,"min":504.4,"max":528.15},{"mes":"2025-04","mediana":235.0,"n":1,"min":235.0,"max":235.0}],"por_municipio":[{"municipio":"Belém","mediana":504.4,"n":3,"min":235.0,"max":528.15}],"ocorrencias":[{"mes":"2025-04","municipio":"Belém","valor_unitario":235.0,"quantidade":1.0,"unidade":"unidade","srp":false,"modalidade_nome":"Dispensa","cnpj_orgao":"00508903000188","sequencial_compra":660},{"mes":"2025-02","municipio":"Belém","valor_unitario":504.4,"quantidade":10.0,"unidade":"unidade","srp":false,"modalidade_nome":"Pregão - Eletrônico","cnpj_orgao":"22980973000177","sequencial_compra":18},{"mes":"2025-02","municipio":"Belém","valor_unitario":528.15,"quantidade":6.0,"unidade":"unidade","srp":false,"modalidade_nome":"Pregão - Eletrônico","cnpj_orgao":"22980973000177","sequencial_compra":18}]}