{"id":"farinha-puba-99e3f56a","nome":"-FARINHA PÚBA","nome_norm":"-farinha puba","categoria":"Alimentação e Gêneros Alimentícios","unidade":"kg","tipo":"M","sneaelis":false,"preco":{"min":12.44,"p25":12.44,"mediana":12.44,"media":12.44,"p75":12.44,"p90":12.44,"max":12.44,"desvio":0.0,"n":2},"srp_pct":0.0,"serie_temporal":[{"mes":"2025-03","mediana":12.44,"n":2,"min":12.44,"max":12.44}],"por_municipio":[{"municipio":"Novo Progresso","mediana":12.44,"n":2,"min":12.44,"max":12.44}],"ocorrencias":[{"mes":"2025-03","municipio":"Novo Progresso","valor_unitario":12.44,"quantidade":120.0,"unidade":"kg","srp":false,"modalidade_nome":"Dispensa","cnpj_orgao":"10221786000120","sequencial_compra":13},{"mes":"2025-03","municipio":"Novo Progresso","valor_unitario":12.44,"quantidade":80.0,"unidade":"kg","srp":false,"modalidade_nome":"Dispensa","cnpj_orgao":"10221786000120","sequencial_compra":18}]}