{"id":"fritadeira-material-estrutura-aco-inoxi-837caf03","nome":"Fritadeira material estrutura: aço inoxidável, potência: 1900, tensão alimentação: 110, capacidade: 5,5, características adicionais: tipo fryer, sem utilizar óleo","nome_norm":"fritadeira material estrutura: aco inoxidavel, potencia: 1900, tensao alimentaca","categoria":"Outros","unidade":"unidade","tipo":"M","sneaelis":false,"preco":{"min":434.9,"p25":466.75,"mediana":498.6,"media":498.6,"p75":530.45,"p90":549.56,"max":562.3,"desvio":90.09,"n":2},"srp_pct":0.0,"serie_temporal":[{"mes":"2025-11","mediana":498.6,"n":2,"min":434.9,"max":562.3}],"por_municipio":[{"municipio":"Belém","mediana":498.6,"n":2,"min":434.9,"max":562.3}],"ocorrencias":[{"mes":"2025-11","municipio":"Belém","valor_unitario":434.9,"quantidade":1.0,"unidade":"unidade","srp":false,"modalidade_nome":"Dispensa","cnpj_orgao":"00394502000144","sequencial_compra":12007},{"mes":"2025-11","municipio":"Belém","valor_unitario":562.3,"quantidade":1.0,"unidade":"unidade","srp":false,"modalidade_nome":"Dispensa","cnpj_orgao":"00394502000144","sequencial_compra":11657}]}