{"id":"inatalacao-manutencao-circuito-fechado-5e0e9ca1","nome":"Inatalação/Manutenção - Circuito Fechado TV","nome_norm":"inatalacao/manutencao - circuito fechado tv","categoria":"Mobiliário e Equipamentos Gerais","unidade":"unidade","tipo":"S","sneaelis":true,"preco":{"min":16978.8,"p25":854603.88,"mediana":1692228.95,"media":1692228.95,"p75":2529854.02,"p90":3032429.07,"max":3367479.1,"desvio":2369161.48,"n":2},"srp_pct":0.0,"serie_temporal":[{"mes":"2025-06","mediana":1692228.95,"n":2,"min":16978.8,"max":3367479.1}],"por_municipio":[{"municipio":"Belém","mediana":1692228.95,"n":2,"min":16978.8,"max":3367479.1}],"ocorrencias":[{"mes":"2025-06","municipio":"Belém","valor_unitario":16978.8,"quantidade":24.0,"unidade":"unidade","srp":false,"modalidade_nome":"Concorrência - Eletrônica","cnpj_orgao":"15126437000305","sequencial_compra":1099},{"mes":"2025-06","municipio":"Belém","valor_unitario":3367479.1,"quantidade":1.0,"unidade":"unidade","srp":false,"modalidade_nome":"Concorrência - Eletrônica","cnpj_orgao":"15126437000305","sequencial_compra":1099}]}