{"id":"limpeza-de-fossa-esgoto-boca-de-lobo-836d3e14","nome":"Limpeza de fossa / esgoto / boca de lobo Limpeza de fossa / esgoto / boca de lobo","nome_norm":"limpeza de fossa / esgoto / boca de lobo limpeza de fossa / esgoto / boca de lob","categoria":"Outros","unidade":"m3","tipo":"S","sneaelis":false,"preco":{"min":1504.17,"p25":8251.04,"mediana":11522.56,"media":181137.32,"p75":184408.83,"p90":493763.53,"max":700000.0,"desvio":345941.7,"n":4},"srp_pct":0.0,"serie_temporal":[{"mes":"2025-03","mediana":700000.0,"n":1,"min":700000.0,"max":700000.0},{"mes":"2025-04","mediana":10500.0,"n":1,"min":10500.0,"max":10500.0},{"mes":"2025-06","mediana":1504.17,"n":1,"min":1504.17,"max":1504.17},{"mes":"2025-12","mediana":12545.11,"n":1,"min":12545.11,"max":12545.11}],"por_municipio":[{"municipio":"Belém","mediana":356272.56,"n":2,"min":12545.11,"max":700000.0},{"municipio":"Marituba","mediana":10500.0,"n":1,"min":10500.0,"max":10500.0},{"municipio":"Santa Izabel do Pará","mediana":1504.17,"n":1,"min":1504.17,"max":1504.17}],"ocorrencias":[{"mes":"2025-06","municipio":"Santa Izabel do Pará","valor_unitario":1504.17,"quantidade":4.0,"unidade":"unidade","srp":false,"modalidade_nome":"Dispensa","cnpj_orgao":"05171699000176","sequencial_compra":20},{"mes":"2025-04","municipio":"Marituba","valor_unitario":10500.0,"quantidade":2.0,"unidade":"unidade","srp":false,"modalidade_nome":"Dispensa","cnpj_orgao":"01611666000149","sequencial_compra":24},{"mes":"2025-12","municipio":"Belém","valor_unitario":12545.11,"quantidade":1.0,"unidade":"unidade","srp":false,"modalidade_nome":"Dispensa","cnpj_orgao":"03204421000122","sequencial_compra":393},{"mes":"2025-03","municipio":"Belém","valor_unitario":700000.0,"quantidade":1.0,"unidade":"m3","srp":false,"modalidade_nome":"Dispensa","cnpj_orgao":"05055033000152","sequencial_compra":16}]}