{"id":"locacao-de-imovel-1de9bb9b","nome":"Locação de imóvel","nome_norm":"locacao de imovel","categoria":"Locação de Bens e Imóveis","unidade":"mes","tipo":"M","sneaelis":false,"preco":{"min":600.0,"p25":1197.5,"mediana":1609.0,"media":5678.07,"p75":3610.0,"p90":9160.0,"max":57000.0,"desvio":11585.28,"n":28},"srp_pct":0.0,"serie_temporal":[{"mes":"2025-01","mediana":1256.99,"n":14,"min":600.0,"max":3000.0},{"mes":"2025-04","mediana":800.0,"n":1,"min":800.0,"max":800.0},{"mes":"2025-05","mediana":5700.0,"n":2,"min":1400.0,"max":10000.0},{"mes":"2025-06","mediana":4000.0,"n":3,"min":1518.0,"max":7000.0},{"mes":"2025-09","mediana":3480.0,"n":3,"min":2500.0,"max":8800.0},{"mes":"2025-10","mediana":57000.0,"n":1,"min":57000.0,"max":57000.0},{"mes":"2025-11","mediana":3174.0,"n":3,"min":2200.0,"max":8000.0},{"mes":"2025-12","mediana":30000.0,"n":1,"min":30000.0,"max":30000.0}],"por_municipio":[{"municipio":"Ipixuna do Pará","mediana":1500.0,"n":21,"min":600.0,"max":7000.0},{"municipio":"Belém","mediana":8800.0,"n":3,"min":2200.0,"max":57000.0},{"municipio":"Ananindeua","mediana":19000.0,"n":2,"min":8000.0,"max":30000.0},{"municipio":"Augusto Corrêa","mediana":3174.0,"n":1,"min":3174.0,"max":3174.0},{"municipio":"Santarém","mediana":10000.0,"n":1,"min":10000.0,"max":10000.0}],"ocorrencias":[{"mes":"2025-01","municipio":"Ipixuna do Pará","valor_unitario":600.0,"quantidade":12.0,"unidade":"mes","srp":false,"modalidade_nome":"Inexigibilidade","cnpj_orgao":"83268011000184","sequencial_compra":102},{"mes":"2025-01","municipio":"Ipixuna do Pará","valor_unitario":600.0,"quantidade":12.0,"unidade":"mes","srp":false,"modalidade_nome":"Inexigibilidade","cnpj_orgao":"83268011000184","sequencial_compra":104},{"mes":"2025-01","municipio":"Ipixuna do Pará","valor_unitario":600.0,"quantidade":12.0,"unidade":"mes","srp":false,"modalidade_nome":"Inexigibilidade","cnpj_orgao":"83268011000184","sequencial_compra":100},{"mes":"2025-01","municipio":"Ipixuna do Pará","valor_unitario":800.0,"quantidade":12.0,"unidade":"mes","srp":false,"modalidade_nome":"Inexigibilidade","cnpj_orgao":"83268011000184","sequencial_compra":99},{"mes":"2025-04","municipio":"Ipixuna do Pará","valor_unitario":800.0,"quantidade":9.0,"unidade":"mes","srp":false,"modalidade_nome":"Inexigibilidade","cnpj_orgao":"83268011000184","sequencial_compra":53},{"mes":"2025-01","municipio":"Ipixuna do Pará","valor_unitario":1000.0,"quantidade":12.0,"unidade":"mes","srp":false,"modalidade_nome":"Inexigibilidade","cnpj_orgao":"83268011000184","sequencial_compra":98},{"mes":"2025-01","municipio":"Ipixuna do Pará","valor_unitario":1100.0,"quantidade":12.0,"unidade":"mes","srp":false,"modalidade_nome":"Inexigibilidade","cnpj_orgao":"83268011000184","sequencial_compra":93},{"mes":"2025-01","municipio":"Ipixuna do Pará","valor_unitario":1230.0,"quantidade":12.0,"unidade":"mes","srp":false,"modalidade_nome":"Inexigibilidade","cnpj_orgao":"83268011000184","sequencial_compra":96},{"mes":"2025-01","municipio":"Ipixuna do Pará","valor_unitario":1283.97,"quantidade":12.0,"unidade":"mes","srp":false,"modalidade_nome":"Inexigibilidade","cnpj_orgao":"83268011000184","sequencial_compra":105},{"mes":"2025-05","municipio":"Ipixuna do Pará","valor_unitario":1400.0,"quantidade":8.0,"unidade":"mes","srp":false,"modalidade_nome":"Inexigibilidade","cnpj_orgao":"83268011000184","sequencial_compra":56},{"mes":"2025-01","municipio":"Ipixuna do Pará","valor_unitario":1500.0,"quantidade":12.0,"unidade":"mes","srp":false,"modalidade_nome":"Inexigibilidade","cnpj_orgao":"83268011000184","sequencial_compra":94},{"mes":"2025-01","municipio":"Ipixuna do Pará","valor_unitario":1500.0,"quantidade":12.0,"unidade":"mes","srp":false,"modalidade_nome":"Inexigibilidade","cnpj_orgao":"83268011000184","sequencial_compra":92},{"mes":"2025-01","municipio":"Ipixuna do Pará","valor_unitario":1500.0,"quantidade":12.0,"unidade":"mes","srp":false,"modalidade_nome":"Inexigibilidade","cnpj_orgao":"83268011000184","sequencial_compra":7},{"mes":"2025-06","municipio":"Ipixuna do Pará","valor_unitario":1518.0,"quantidade":7.0,"unidade":"mes","srp":false,"modalidade_nome":"Inexigibilidade","cnpj_orgao":"83268011000184","sequencial_compra":68},{"mes":"2025-01","municipio":"Ipixuna do Pará","valor_unitario":1700.0,"quantidade":12.0,"unidade":"mes","srp":false,"modalidade_nome":"Inexigibilidade","cnpj_orgao":"83268011000184","sequencial_compra":97},{"mes":"2025-11","municipio":"Belém","valor_unitario":2200.0,"quantidade":12.0,"unidade":"mes","srp":false,"modalidade_nome":"Inexigibilidade","cnpj_orgao":"00368105000106","sequencial_compra":50},{"mes":"2025-09","municipio":"Ipixuna do Pará","valor_unitario":2500.0,"quantidade":3.0,"unidade":"mes","srp":false,"modalidade_nome":"Inexigibilidade","cnpj_orgao":"83268011000184","sequencial_compra":98},{"mes":"2025-01","municipio":"Ipixuna do Pará","valor_unitario":2700.0,"quantidade":12.0,"unidade":"mes","srp":false,"modalidade_nome":"Inexigibilidade","cnpj_orgao":"83268011000184","sequencial_compra":95},{"mes":"2025-01","municipio":"Ipixuna do Pará","valor_unitario":3000.0,"quantidade":12.0,"unidade":"mes","srp":false,"modalidade_nome":"Inexigibilidade","cnpj_orgao":"83268011000184","sequencial_compra":101},{"mes":"2025-11","municipio":"Augusto Corrêa","valor_unitario":3174.0,"quantidade":12.0,"unidade":"mes","srp":false,"modalidade_nome":"Inexigibilidade","cnpj_orgao":"04873600000115","sequencial_compra":186},{"mes":"2025-09","municipio":"Ipixuna do Pará","valor_unitario":3480.0,"quantidade":5.0,"unidade":"mes","srp":false,"modalidade_nome":"Inexigibilidade","cnpj_orgao":"83268011000184","sequencial_compra":90},{"mes":"2025-06","municipio":"Ipixuna do Pará","valor_unitario":4000.0,"quantidade":7.0,"unidade":"mes","srp":false,"modalidade_nome":"Inexigibilidade","cnpj_orgao":"83268011000184","sequencial_compra":69},{"mes":"2025-06","municipio":"Ipixuna do Pará","valor_unitario":7000.0,"quantidade":7.0,"unidade":"mes","srp":false,"modalidade_nome":"Inexigibilidade","cnpj_orgao":"83268011000184","sequencial_compra":66},{"mes":"2025-11","municipio":"Ananindeua","valor_unitario":8000.0,"quantidade":12.0,"unidade":"mes","srp":false,"modalidade_nome":"Inexigibilidade","cnpj_orgao":"05058441000168","sequencial_compra":147},{"mes":"2025-09","municipio":"Belém","valor_unitario":8800.0,"quantidade":1.0,"unidade":"mes","srp":false,"modalidade_nome":"Inexigibilidade","cnpj_orgao":"00368105000106","sequencial_compra":35},{"mes":"2025-05","municipio":"Santarém","valor_unitario":10000.0,"quantidade":48.0,"unidade":"mes","srp":false,"modalidade_nome":"Inexigibilidade","cnpj_orgao":"05182233001814","sequencial_compra":1},{"mes":"2025-12","municipio":"Ananindeua","valor_unitario":30000.0,"quantidade":12.0,"unidade":"mes","srp":false,"modalidade_nome":"Inexigibilidade","cnpj_orgao":"05058441000168","sequencial_compra":175},{"mes":"2025-10","municipio":"Belém","valor_unitario":57000.0,"quantidade":60.0,"unidade":"mes","srp":false,"modalidade_nome":"Inexigibilidade","cnpj_orgao":"00368105000106","sequencial_compra":45}]}