{"id":"memoria-ram-e0f6727e","nome":"Memória Ram","nome_norm":"memoria ram","categoria":"Informática e TI","unidade":"unidade","tipo":"M","sneaelis":true,"preco":{"min":96.37,"p25":97.7,"mediana":99.03,"media":99.55,"p75":101.13,"p90":102.4,"max":103.24,"desvio":3.46,"n":3},"srp_pct":0.0,"serie_temporal":[{"mes":"2025-03","mediana":96.37,"n":1,"min":96.37,"max":96.37},{"mes":"2025-05","mediana":103.24,"n":1,"min":103.24,"max":103.24},{"mes":"2025-12","mediana":99.03,"n":1,"min":99.03,"max":99.03}],"por_municipio":[{"municipio":"Belém","mediana":99.03,"n":3,"min":96.37,"max":103.24}],"ocorrencias":[{"mes":"2025-03","municipio":"Belém","valor_unitario":96.37,"quantidade":120.0,"unidade":"unidade","srp":false,"modalidade_nome":"Pregão - Eletrônico","cnpj_orgao":"22980973000177","sequencial_compra":28},{"mes":"2025-12","municipio":"Belém","valor_unitario":99.03,"quantidade":30.0,"unidade":"unidade","srp":false,"modalidade_nome":"Pregão - Eletrônico","cnpj_orgao":"00368105000106","sequencial_compra":56},{"mes":"2025-05","municipio":"Belém","valor_unitario":103.24,"quantidade":5.0,"unidade":"unidade","srp":false,"modalidade_nome":"Dispensa","cnpj_orgao":"00394502000144","sequencial_compra":5148}]}