{"id":"pufe-5cc64aea","nome":"Pufe","nome_norm":"pufe","categoria":"Outros","unidade":"unidade","tipo":"M","sneaelis":false,"preco":{"min":135.0,"p25":371.59,"mediana":584.27,"media":520.53,"p75":733.21,"p90":760.43,"max":778.58,"desvio":293.92,"n":4},"srp_pct":100.0,"serie_temporal":[{"mes":"2025-03","mediana":718.09,"n":3,"min":450.45,"max":778.58},{"mes":"2025-04","mediana":135.0,"n":1,"min":135.0,"max":135.0}],"por_municipio":[{"municipio":"Belém","mediana":584.27,"n":4,"min":135.0,"max":778.58}],"ocorrencias":[{"mes":"2025-04","municipio":"Belém","valor_unitario":135.0,"quantidade":840.0,"unidade":"unidade","srp":true,"modalidade_nome":"Pregão - Eletrônico","cnpj_orgao":"35747782000101","sequencial_compra":5},{"mes":"2025-03","municipio":"Belém","valor_unitario":450.45,"quantidade":60.0,"unidade":"unidade","srp":true,"modalidade_nome":"Pregão - Eletrônico","cnpj_orgao":"03593364000110","sequencial_compra":4},{"mes":"2025-03","municipio":"Belém","valor_unitario":718.09,"quantidade":60.0,"unidade":"unidade","srp":true,"modalidade_nome":"Pregão - Eletrônico","cnpj_orgao":"03593364000110","sequencial_compra":4},{"mes":"2025-03","municipio":"Belém","valor_unitario":778.58,"quantidade":60.0,"unidade":"unidade","srp":true,"modalidade_nome":"Pregão - Eletrônico","cnpj_orgao":"03593364000110","sequencial_compra":4}]}