{"id":"refrigerante-1c734dd7","nome":"REFRIGERANTE","nome_norm":"refrigerante","categoria":"Alimentação e Gêneros Alimentícios","unidade":"unidade","tipo":"M","sneaelis":false,"preco":{"min":3.92,"p25":5.55,"mediana":6.56,"media":6.72,"p75":7.1,"p90":8.68,"max":11.97,"desvio":2.44,"n":8},"srp_pct":75.0,"serie_temporal":[{"mes":"2025-02","mediana":11.97,"n":1,"min":11.97,"max":11.97},{"mes":"2025-06","mediana":3.92,"n":1,"min":3.92,"max":3.92},{"mes":"2025-12","mediana":6.56,"n":6,"min":4.5,"max":7.27}],"por_municipio":[{"municipio":"Itaituba","mediana":6.56,"n":6,"min":4.5,"max":7.27},{"municipio":"Belém","mediana":3.92,"n":1,"min":3.92,"max":3.92},{"municipio":"Tucuruí","mediana":11.97,"n":1,"min":11.97,"max":11.97}],"ocorrencias":[{"mes":"2025-06","municipio":"Belém","valor_unitario":3.92,"quantidade":500.0,"unidade":"lata 350,00 ml","srp":false,"modalidade_nome":"Dispensa","cnpj_orgao":"00394452000103","sequencial_compra":13141},{"mes":"2025-12","municipio":"Itaituba","valor_unitario":4.5,"quantidade":400.0,"unidade":"lata 350,00 ml","srp":true,"modalidade_nome":"Pregão - Eletrônico","cnpj_orgao":"00394452000103","sequencial_compra":24218},{"mes":"2025-12","municipio":"Itaituba","valor_unitario":5.9,"quantidade":500.0,"unidade":"garrafa 2,00 l","srp":true,"modalidade_nome":"Pregão - Eletrônico","cnpj_orgao":"00394452000103","sequencial_compra":24218},{"mes":"2025-12","municipio":"Itaituba","valor_unitario":6.33,"quantidade":600.0,"unidade":"garrafa 2,00 l","srp":true,"modalidade_nome":"Pregão - Eletrônico","cnpj_orgao":"00394452000103","sequencial_compra":24218},{"mes":"2025-12","municipio":"Itaituba","valor_unitario":6.79,"quantidade":900.0,"unidade":"garrafa 2,50 l","srp":true,"modalidade_nome":"Pregão - Eletrônico","cnpj_orgao":"00394452000103","sequencial_compra":24218},{"mes":"2025-12","municipio":"Itaituba","valor_unitario":7.05,"quantidade":500.0,"unidade":"garrafa 2,00 l","srp":true,"modalidade_nome":"Pregão - Eletrônico","cnpj_orgao":"00394452000103","sequencial_compra":24218},{"mes":"2025-12","municipio":"Itaituba","valor_unitario":7.27,"quantidade":900.0,"unidade":"garrafa 2,00 l","srp":true,"modalidade_nome":"Pregão - Eletrônico","cnpj_orgao":"00394452000103","sequencial_compra":24218},{"mes":"2025-02","municipio":"Tucuruí","valor_unitario":11.97,"quantidade":400.0,"unidade":"unidade","srp":false,"modalidade_nome":"Pregão - Eletrônico","cnpj_orgao":"05845664000175","sequencial_compra":4}]}