{"id":"tratores-de-esteira-motor-a-diesel-pot-c9fe3f1d","nome":"Tratores de esteira, motor a diesel, potência mínima 100 HP e com capacidade da lâmina de 2 m com peças, pneus, operador e combustível por conta do contratante, em bom estado de conservação.","nome_norm":"tratores de esteira, motor a diesel, potencia minima 100 hp e com capacidade da ","categoria":"Combustíveis e Lubrificantes","unidade":"hora","tipo":"M","sneaelis":false,"preco":{"min":487.77,"p25":489.58,"mediana":491.38,"media":491.38,"p75":493.19,"p90":494.28,"max":495.0,"desvio":5.11,"n":2},"srp_pct":100.0,"serie_temporal":[{"mes":"2025-02","mediana":495.0,"n":1,"min":495.0,"max":495.0},{"mes":"2025-10","mediana":487.77,"n":1,"min":487.77,"max":487.77}],"por_municipio":[{"municipio":"Uruará","mediana":491.38,"n":2,"min":487.77,"max":495.0}],"ocorrencias":[{"mes":"2025-10","municipio":"Uruará","valor_unitario":487.77,"quantidade":3000.0,"unidade":"hora","srp":true,"modalidade_nome":"Pregão - Eletrônico","cnpj_orgao":"34593541000192","sequencial_compra":85},{"mes":"2025-02","municipio":"Uruará","valor_unitario":495.0,"quantidade":2000.0,"unidade":"hora","srp":true,"modalidade_nome":"Pregão - Eletrônico","cnpj_orgao":"34593541000192","sequencial_compra":16}]}